autogpt_research_agent/__init__.py
autogpt_research_agent/__main__.py
autogpt_research_agent/executor.py
autogpt_research_agent/memory.py
autogpt_research_agent/planner.py
autogpt_research_agent/reporter.py
autogpt_research_agent/ui_app.py
autogpt_research_agent_ramon-0.2.3.dist-info/METADATA
autogpt_research_agent_ramon-0.2.3.dist-info/WHEEL
autogpt_research_agent_ramon-0.2.3.dist-info/entry_points.txt
autogpt_research_agent_ramon-0.2.3.dist-info/top_level.txt
autogpt_research_agent_ramon-0.2.3.dist-info/RECORD
