Metadata-Version: 2.4
Name: autogpt-research-agent-ramon
Version: 0.2.3
Summary: Autonomous Research Agent: plan, execute, remember, and report with Python + LLM
Author-email: Your Name <you@example.com>
License-Expression: MIT
Project-URL: Homepage, https://github.com/ramonbnuezjr/autogpt-research-agent
Project-URL: Source, https://github.com/ramonbnuezjr/autogpt-research-agent
Keywords: AI,agent,RAG,LLM
Classifier: Programming Language :: Python :: 3
Requires-Dist: openai
Requires-Dist: python-dotenv
Requires-Dist: requests
Requires-Dist: beautifulsoup4
Requires-Dist: PyYAML>=6.0
Requires-Dist: pytest
Provides-Extra: web
Requires-Dist: flask; extra == "web"
Requires-Dist: streamlit; extra == "web"
Provides-Extra: dev
Requires-Dist: black; extra == "dev"
Requires-Dist: ruff; extra == "dev"
Requires-Dist: pytest; extra == "dev"
